migrations/0001_initial.py
migrations/0002_log.py
migrations/0003_auto_20160715_0100.py
migrations/__init__.py
plugins/__init__.py
plugins/actions.py
plugins/aggregation.py
plugins/ajax.py
plugins/auth.py
plugins/batch.py
plugins/bookmark.py
plugins/chart.py
plugins/comments.py
plugins/details.py
plugins/editable.py
plugins/excel.py
plugins/export.py
plugins/filters.py
plugins/images.py
plugins/inline.py
plugins/language.py
plugins/layout.py
plugins/mobile.py
plugins/multiselect.py
plugins/passwords.py
plugins/portal.py
plugins/quickfilter.py
plugins/quickform.py
plugins/refresh.py
plugins/relate.py
plugins/relfield.py
plugins/sitemenu.py
plugins/sortablelist.py
plugins/themes.py
plugins/topnav.py
plugins/ueditor.py
plugins/utils.py
plugins/wizard.py
plugins/xversion.py
templatetags/__init__.py
templatetags/xadmin_tags.py
views/__init__.py
views/base.py
views/dashboard.py
views/delete.py
views/detail.py
views/edit.py
views/form.py
views/list.py
views/website.py
ymxadmin-1.0.2.dist-info/METADATA
ymxadmin-1.0.2.dist-info/WHEEL
ymxadmin-1.0.2.dist-info/top_level.txt
ymxadmin-1.0.2.dist-info/RECORD
